{
"МатериальныеЗапасы": [
{
"Номенклатура": "Пара трансиверов SFP, BiDi, Single Mode, LC, 3 км",
"НоменклатураКод": "00-000000000456",
"Количество": 2,
"МОЛ": "Дроздова Татьяна Викторовна"
},
{
"Номенклатура": "DMD-чип 1076-6038B/Матрица 1076-6038B",
"НоменклатураКод": "00-000000000448",
"Количество": 1,
"МОЛ": "Дроздова Татьяна Викторовна"
},
{
"Номенклатура": "DMD-чип 1280-6038B/Матрица 1280-6038B",
"НоменклатураКод": "00-000000000447",
"Количество": 1,
"МОЛ": "Дроздова Татьяна Викторовна"
},
{
"Номенклатура": "Hyperline FC-D2-9-FC/UR-H-50M-LS ZH-YL Патч-корд",
"НоменклатураКод": "00-000000008871",
"Количество": 2,
"МОЛ": "Дроздова Татьяна Викторовна"
},
{
"Номенклатура": "REC PLA пластик1,75 Натуральный,страна происхождения Россия0,75кг",
"НоменклатураКод": "00-000000007993",
"Количество": 1,
"МОЛ": "Дроздова Татьяна Викторовна"
},
{
"Номенклатура": "REC PLA пластик1,75 Натуральный,страна происхождения Россия0,75кг",
"НоменклатураКод": "00-000000007992",
"Количество": 87,
"МОЛ": "Дроздова Татьяна Викторовна"
},
{
"Номенклатура": "Usb провод для принтера 1.8 м",
"НоменклатураКод": "00-000000000484",
"Количество": 10,
"МОЛ": "Дроздова Татьяна Викторовна"
},
{
"Номенклатура": "Usb провод для принтера 3 м",
"НоменклатураКод": "00-000000000482",
"Количество": 5,
"МОЛ": "Дроздова Татьяна Викторовна"
},
{
"Номенклатура": "Usb провод для принтера 5 м",
"НоменклатураКод": "00-000000000483",
"Количество": 5,
"МОЛ": "Дроздова Татьяна Викторовна"
},
{
"Номенклатура": "Адаптер подключения HDD2.5 в отсек привода ноутбука DEXP",
"НоменклатураКод": "00-000000003951",
"Количество": 1,
"МОЛ": "Дроздова Татьяна Викторовна"
},
{
"Номенклатура": "АКБ-7 Аккумулятор 12V",
"НоменклатураКод": "00-000000007536",
"Количество": 5,
"МОЛ": "Дроздова Татьяна Викторовна"
},
{
"Номенклатура": "АКБ-7 Аккумулятор SECURITY 12v",
"НоменклатураКод": "00-000000007516",
"Количество": 10,
"МОЛ": "Дроздова Татьяна Викторовна"
},
{
"Номенклатура": "Аккумулятор",
"НоменклатураКод": "П00000001578",
"Количество": 1,
"МОЛ": "Дроздова Татьяна Викторовна"
},
{
"Номенклатура": "Аккумулятор CSB HRL 1234W F2FR (12V, 9Ah)",
"НоменклатураКод": "00-000000005582",
"Количество": 20,
"МОЛ": "Дроздова Татьяна Викторовна"
},
{
"Номенклатура": "Барабан Kyocera FS-1040/1060DN",
"НоменклатураКод": "00-000000008830",
"Количество": 10,
"МОЛ": "Дроздова Татьяна Викторовна"
},
{
"Номенклатура": "Блок питания AirMax A8-400W ATX",
"НоменклатураКод": "ОСОООООП9513",
"Количество": 5,
"МОЛ": "Дроздова Татьяна Викторовна"
},
{
"Номенклатура": "Блок питания Ginzzu CA450 ATX v2.3 450w 120mm",
"НоменклатураКод": "00-000000007495",
"Количество": 5,
"МОЛ": "Дроздова Татьяна Викторовна"
},
{
"Номенклатура": "Блок питания аккумуляторный ДЗ883450-PCB",
"НоменклатураКод": "ОСОООООО5740",
"Количество": 4,
"МОЛ": "Дроздова Татьяна Викторовна"
},
{
"Номенклатура": "Блок проявки {FS-2100/ FS-4100DN/ FS-4200DN/.../ ECOSYS M3",
"НоменклатураКод": "00-000000000467",
"Количество": 1,
"МОЛ": "Дроздова Татьяна Викторовна"
},
{
"Номенклатура": "Блок проявки NVP совместимый NV-DV-1140",
"НоменклатураКод": "00-000000004488",
"Количество": 3,
"МОЛ": "Дроздова Татьяна Викторовна"
},
{
"Номенклатура": "Блок Фотобарабана (P2040dn,P2040dw,P2235dn)",
"НоменклатураКод": "00-000000000445",
"Количество": 2,
"МОЛ": "Дроздова Татьяна Викторовна"
},
{
"Номенклатура": "Блок фотобарабана Kyocera DK-1110",
"НоменклатураКод": "ОСОООООП9607",
"Количество": 3,
"МОЛ": "Дроздова Татьяна Викторовна"
},
{
"Номенклатура": "Веб-камера DEFENDER",
"НоменклатураКод": "00-000000007496",
"Количество": 5,
"МОЛ": "Дроздова Татьяна Викторовна"
},
{
"Номенклатура": "Вентилятор Deepcool DP-MCAL-HT GAMMA HUNTER",
"НоменклатураКод": "00-000000005598",
"Количество": 10,
"МОЛ": "Дроздова Татьяна Викторовна"
},
{
"Номенклатура": "Вентилятор NIDEC TA 150DC 12V 40х40х28",
"НоменклатураКод": "00-000000005590",
"Количество": 4,
"МОЛ": "Дроздова Татьяна Викторовна"
},
{
"Номенклатура": "Внешний жесткий диск 8 Tb Seagate Backup Plus .3.5 ,USB 3.0",
"НоменклатураКод": "ОСОООООП6531",
"Количество": 1,
"МОЛ": "Дроздова Татьяна Викторовна"
},
{
"Номенклатура": "Внешний жесткий диск USB3 1TB EXT BLACK",
"НоменклатураКод": "00-000000008842",
"Количество": 5,
"МОЛ": "Дроздова Татьяна Викторовна"
},
{
"Номенклатура": "Гибкая гофрированная легкая труба",
"НоменклатураКод": "00-000000008874",
"Количество": 1,
"МОЛ": "Дроздова Татьяна Викторовна"
},
{
"Номенклатура": "Драйвер шагового двигателя на базе микросхемы DRV8825",
"НоменклатураКод": "ОСОООООП9502",
"Количество": 15,
"МОЛ": "Дроздова Татьяна Викторовна"
},
{
"Номенклатура": "Драм - юнит Hi-Blask (HB-CF219A) lkz HP LJ Pro M 104/MFP M132.12K",
"НоменклатураКод": "00-000000007801",
"Количество": 3,
"МОЛ": "Дроздова Татьяна Викторовна"
},
{
"Номенклатура": "Драм-юнит Cet CET 471064",
"НоменклатураКод": "00-000000007521",
"Количество": 3,
"МОЛ": "Дроздова Татьяна Викторовна"
},
{
"Номенклатура": "Дуплекс DU-480 (совм.) Kyocera TASKalfa 1800/2200/1801/2201",
"НоменклатураКод": "00-000000005610",
"Количество": 1,
"МОЛ": "Дроздова Татьяна Викторовна"
},
{
"Номенклатура": "Жесткий диск 1TB Toshiba P300 64Mm",
"НоменклатураКод": "ОСОООООП9511",
"Количество": 29,
"МОЛ": "Дроздова Татьяна Викторовна"
},
{
"Номенклатура": "Жесткий диск HDD 1Tb SATA 6Gb/s Seagate Exos",
"НоменклатураКод": "00-000000005591",
"Количество": 1,
"МОЛ": "Дроздова Татьяна Викторовна"
},
{
"Номенклатура": "Жесткий диск HP 653952-01 600GB 15K 6G LFF SAS 3.5\"",
"НоменклатураКод": "00-000000005580",
"Количество": 1,
"МОЛ": "Дроздова Татьяна Викторовна"
},
{
"Номенклатура": "Жесткий диск HP SAS 3,5 дюйма",
"НоменклатураКод": "ОСОООООП9521",
"Количество": 2,
"МОЛ": "Дроздова Татьяна Викторовна"
},
{
"Номенклатура": "Жесткий диск SSD AMD Radeon 2.5'' 256GB",
"НоменклатураКод": "00-000000005602",
"Количество": 26,
"МОЛ": "Дроздова Татьяна Викторовна"
},
{
"Номенклатура": "Жесткий диск Toshiba USB 3/0 1TbHDTB410EK3AACanvio Basics2.5 черный",
"НоменклатураКод": "ОСОООООП9978",
"Количество": 2,
"МОЛ": "Дроздова Татьяна Викторовна"
},
{
"Номенклатура": "ИБП PowerCom",
"НоменклатураКод": "00-000000007290",
"Количество": 1,
"МОЛ": "Дроздова Татьяна Викторовна"
},
{
"Номенклатура": "Инструмент обжимной НТ-2008А",
"НоменклатураКод": "ОС0000000341",
"Количество": 2,
"МОЛ": "Дроздова Татьяна Викторовна"
},
{
"Номенклатура": "Кабель Cabeus витая пара UTP-4P-Cat 5 SOLID-BL UTP",
"НоменклатураКод": "00-000000006907",
"Количество": 4,
"МОЛ": "Дроздова Татьяна Викторовна"
},
{
"Номенклатура": "Кабель Cabeus витая пара UTP-4P*Cat5-SOLID-BL UTP",
"НоменклатураКод": "00-000000006911",
"Количество": 5,
"МОЛ": "Дроздова Татьяна Викторовна"
},
{
"Номенклатура": "Кабель Cabeus витая пара,категория 5е,4пары,051мм,одножильный,синий UTP-4P-Cat5e-SOLID-BL",
"НоменклатураКод": "00-000000009265",
"Количество": 4,
"МОЛ": "Дроздова Татьяна Викторовна"
},
{
"Номенклатура": "Кабель DVI-D toDVI-D",
"НоменклатураКод": "ОСОООООП2473",
"Количество": 5,
"МОЛ": "Дроздова Татьяна Викторовна"
},
{
"Номенклатура": "Кабель Espada (E HDMI M-VGAF20) кабель-адаптер HDMI -) + аудио",
"НоменклатураКод": "00-000000000469",
"Количество": 1,
"МОЛ": "Дроздова Татьяна Викторовна"
},
{
"Номенклатура": "Кабель Exegate EX194332RUS кабель НDMI (19М-19М) 1,8м",
"НоменклатураКод": "00-000000003184",
"Количество": 15,
"МОЛ": "Дроздова Татьяна Викторовна"
},
{
"Номенклатура": "Кабель HDMI-HDMI 1,8м",
"НоменклатураКод": "П00000001558",
"Количество": 5,
"МОЛ": "Дроздова Татьяна Викторовна"
},
{
"Номенклатура": "Кабель HDMI-HDMI 5м",
"НоменклатураКод": "П00000001557",
"Количество": 5,
"МОЛ": "Дроздова Татьяна Викторовна"
},
{
"Номенклатура": "Кабель USB 2.0 Am-BM 1.8м",
"НоменклатураКод": "ОСОООООП4362",
"Количество": 7,
"МОЛ": "Дроздова Татьяна Викторовна"
},
{
"Номенклатура": "Кабель USB 2.0,  1.8 m",
"НоменклатураКод": "ОСОООООП5961",
"Количество": 5,
"МОЛ": "Дроздова Татьяна Викторовна"
},
{
"Номенклатура": "Кабель USB-разветвитель DEXP 100см",
"НоменклатураКод": "П00000001426",
"Количество": 1,
"МОЛ": "Дроздова Татьяна Викторовна"
},
{
"Номенклатура": "Кабель UTP 4 пары кат.5е <305 м>",
"НоменклатураКод": "00-000000005589",
"Количество": 2,
"МОЛ": "Дроздова Татьяна Викторовна"
},
{
"Номенклатура": "Кабель видео Buro DVI-D(m)DVI-D(m) 1,8м",
"НоменклатураКод": "00-000000004485",
"Количество": 15,
"МОЛ": "Дроздова Татьяна Викторовна"
},
{
"Номенклатура": "Кабель витая пара UTP (U/UTP), категория 5е, 4 пары (24 AWG), 305м",
"НоменклатураКод": "00-000000005584",
"Количество": 8,
"МОЛ": "Дроздова Татьяна Викторовна"
},
{
"Номенклатура": "Кабель монитор VCOM VVG6448-10M(C)-(S)VGA card (15M-15M) 10м 2фильтра",
"НоменклатураКод": "ОСОООООП5650",
"Количество": 2,
"МОЛ": "Дроздова Татьяна Викторовна"
},
{
"Номенклатура": "Кабель ТV-COM CG150S-3м,Кабель HDMI toHDMI (19м-19м) 3м ver 1.4.страна происхождения Китай",
"НоменклатураКод": "00-000000009159",
"Количество": 4,
"МОЛ": "Дроздова Татьяна Викторовна"
},
{
"Номенклатура": "Кабель удлинительный TELECOM USB2.0",
"НоменклатураКод": "00-000000008839",
"Количество": 5,
"МОЛ": "Дроздова Татьяна Викторовна"
},
{
"Номенклатура": "Кабель-канал 40*16 ЭЛЕКОР",
"НоменклатураКод": "00-000000005600",
"Количество": 120,
"МОЛ": "Дроздова Татьяна Викторовна"
},
{
"Номенклатура": "Кабель-канал 40*20мм без перегородки с крышкой длина 2,10м",
"НоменклатураКод": "00-000000005603",
"Количество": 84,
"МОЛ": "Дроздова Татьяна Викторовна"
},
{
"Номенклатура": "Кабель-канал 40*25 пластик ИЭК",
"НоменклатураКод": "00-000000006899",
"Количество": 100,
"МОЛ": "Дроздова Татьяна Викторовна"
},
{
"Номенклатура": "Кабель-канал 40*25L2000 пластик ЭЛЕКОР ИЭК СКК10-040-025-1-КО1",
"НоменклатураКод": "00-000000009264",
"Количество": 24,
"МОЛ": "Дроздова Татьяна Викторовна"
},
{
"Номенклатура": "Камера для Raspberry Pi Model B+/2/3",
"НоменклатураКод": "ОСОООООП9500",
"Количество": 3,
"МОЛ": "Дроздова Татьяна Викторовна"
},
{
"Номенклатура": "Карта памяти Kingston USB Drive 32GB",
"НоменклатураКод": "00-000000005601",
"Количество": 10,
"МОЛ": "Дроздова Татьяна Викторовна"
},
{
"Номенклатура": "Карта памяти Ultra MicroSD 16Гб",
"НоменклатураКод": "ОСОООООП9503",
"Количество": 8,
"МОЛ": "Дроздова Татьяна Викторовна"
},
{
"Номенклатура": "Карта сетевая D-Link DGE-528T",
"НоменклатураКод": "ОС0000004906",
"Количество": 6,
"МОЛ": "Дроздова Татьяна Викторовна"
},
{
"Номенклатура": "Картридж Brother IN-2375",
"НоменклатураКод": "00-000000000571",
"Количество": 1,
"МОЛ": "Дроздова Татьяна Викторовна"
},
{
"Номенклатура": "Картридж GP-CF 283X/737 дляHP Laser Jet PRO MFP M127 fn/M127 fm/M201 n/dw/M Canon",
"НоменклатураКод": "00-000000007541",
"Количество": 2,
"МОЛ": "Дроздова Татьяна Викторовна"
},
{
"Номенклатура": "Картридж NV Print совместимый Canon FX-10 черный",
"НоменклатураКод": "00-000000008837",
"Количество": 10,
"МОЛ": "Дроздова Татьяна Викторовна"
},
{
"Номенклатура": "Картридж NVP совместимый NV-TK(3000k)",
"НоменклатураКод": "00-000000008838",
"Количество": 4,
"МОЛ": "Дроздова Татьяна Викторовна"
},
{
"Номенклатура": "Картридж NVP совместимый ТМ-СА218AT",
"НоменклатураКод": "00-000000008836",
"Количество": 3,
"МОЛ": "Дроздова Татьяна Викторовна"
},
{
"Номенклатура": "Клавиатура",
"НоменклатураКод": "П00000001565",
"Количество": 18,
"МОЛ": "Дроздова Татьяна Викторовна"
},
{
"Номенклатура": "Клавиатура CBR KB 112 USB",
"НоменклатураКод": "ОСОООООП9522",
"Количество": 3,
"МОЛ": "Дроздова Татьяна Викторовна"
},
{
"Номенклатура": "Клавиатура Defender Accent клавиатура 45720",
"НоменклатураКод": "00-000000007533",
"Количество": 1,
"МОЛ": "Дроздова Татьяна Викторовна"
},
{
"Номенклатура": "Клавиатура Dialog PS/2",
"НоменклатураКод": "ОСОООООО9877",
"Количество": 1,
"МОЛ": "Дроздова Татьяна Викторовна"
},
{
"Номенклатура": "Клавиатура Genius KB-110X.Black.USB",
"НоменклатураКод": "ОСОООООП6277",
"Количество": 1,
"МОЛ": "Дроздова Татьяна Викторовна"
},
{
"Номенклатура": "Клавиатура OKLICK",
"НоменклатураКод": "ОСОООООП1035",
"Количество": 2,
"МОЛ": "Дроздова Татьяна Викторовна"
},
{
"Номенклатура": "Клавиатура Oklick 180M черный",
"НоменклатураКод": "00-000000000433",
"Количество": 5,
"МОЛ": "Дроздова Татьяна Викторовна"
},
{
"Номенклатура": "Клавиатура PS/2",
"НоменклатураКод": "ОС0000010449",
"Количество": 3,
"МОЛ": "Дроздова Татьяна Викторовна"
},
{
"Номенклатура": "Клавиатура PS/2",
"НоменклатураКод": "ОСОООООП3659",
"Количество": 1,
"МОЛ": "Дроздова Татьяна Викторовна"
},
{
"Номенклатура": "Клавиатура USB Defender",
"НоменклатураКод": "ОСОООООО8769",
"Количество": 2,
"МОЛ": "Дроздова Татьяна Викторовна"
},
{
"Номенклатура": "Клавиатура, мышь Oklick 175M черный",
"НоменклатураКод": "00-000000000431",
"Количество": 4,
"МОЛ": "Дроздова Татьяна Викторовна"
},
{
"Номенклатура": "Колонки 2.0 Оклик ОК-116 (6Вт, питание - USB порт)",
"НоменклатураКод": "00-000000004708",
"Количество": 2,
"МОЛ": "Дроздова Татьяна Викторовна"
},
{
"Номенклатура": "Коммутатор Mercusys MS108 8 портов Ethernet 100 Мбит/с",
"НоменклатураКод": "00-000000008850",
"Количество": 3,
"МОЛ": "Дроздова Татьяна Викторовна"
},
{
"Номенклатура": "Конденсатор э/л 1000мк х 16в",
"НоменклатураКод": "ОСОООООП9672",
"Количество": 30,
"МОЛ": "Дроздова Татьяна Викторовна"
},
{
"Номенклатура": "Конденсатор э/л 1000мк х 35в",
"НоменклатураКод": "ОСОООООП9674",
"Количество": 60,
"МОЛ": "Дроздова Татьяна Викторовна"
},
{
"Номенклатура": "Конденсатор э/л 470мк х 25в",
"НоменклатураКод": "ОСОООООП9664",
"Количество": 30,
"МОЛ": "Дроздова Татьяна Викторовна"
},
{
"Номенклатура": "Конденсатор э/л 470мк х 35в",
"НоменклатураКод": "ОСОООООП9665",
"Количество": 30,
"МОЛ": "Дроздова Татьяна Викторовна"
},
{
"Номенклатура": "Кулер PCCooler GI-X4S (Al +Cu,4тепловых трубок, 800-1600 об/мин, 18-30,6 дБ, TDP 145w, FRGB, 4-pin)",
"НоменклатураКод": "00-000000003034",
"Количество": 1,
"МОЛ": "Дроздова Татьяна Викторовна"
},
{
"Номенклатура": "Лампа Osram P-VIP 280/0.9 E20.9n для проектора",
"НоменклатураКод": "00-000000000416",
"Количество": 3,
"МОЛ": "Дроздова Татьяна Викторовна"
},
{
"Номенклатура": "Лампа Osram P-VIP 280/0/9 E20.8 для проектора (совместимая без модуля)",
"НоменклатураКод": "00-000000007788",
"Количество": 5,
"МОЛ": "Дроздова Татьяна Викторовна"
},
{
"Номенклатура": "Лампа для OPTOMA W307USTi",
"НоменклатураКод": "ОСОООООО8781",
"Количество": 1,
"МОЛ": "Дроздова Татьяна Викторовна"
},
{
"Номенклатура": "Лампа для проектора Acer p527li (EC.j8700.001)",
"НоменклатураКод": "ОСОООООП3672",
"Количество": 1,
"МОЛ": "Дроздова Татьяна Викторовна"
},
{
"Номенклатура": "Лампа для проектора Optoma Osram p- vip 280/0.9 e 20.9n",
"НоменклатураКод": "П00000001560",
"Количество": 1,
"МОЛ": "Дроздова Татьяна Викторовна"
},
{
"Номенклатура": "Лампа для проектора VT40LP оригинальная с модулем",
"НоменклатураКод": "ОСОООООП9687",
"Количество": 1,
"МОЛ": "Дроздова Татьяна Викторовна"
},
{
"Номенклатура": "Лампа для проектора VT85LP",
"НоменклатураКод": "ОСОООООП9688",
"Количество": 1,
"МОЛ": "Дроздова Татьяна Викторовна"
},
{
"Номенклатура": "Материнская плата ASUS PRIME H310M-R R2.0",
"НоменклатураКод": "ОСОООООП9518",
"Количество": 4,
"МОЛ": "Дроздова Татьяна Викторовна"
},
{
"Номенклатура": "Материнская плата Asus PRIME H510M-R R2.0-SI Soc-1200 intel H470",
"НоменклатураКод": "00-000000008819",
"Количество": 5,
"МОЛ": "Дроздова Татьяна Викторовна"
},
{
"Номенклатура": "Материнская плата Biostar LGA1150 H81",
"НоменклатураКод": "00-000000005594",
"Количество": 2,
"МОЛ": "Дроздова Татьяна Викторовна"
},
{
"Номенклатура": "Материнская плата Biostar LGA1155 H61",
"НоменклатураКод": "00-000000005595",
"Количество": 2,
"МОЛ": "Дроздова Татьяна Викторовна"
},
{
"Номенклатура": "Материнская плата Gigabyte H310M S2 (2.0)",
"НоменклатураКод": "00-000000000427",
"Количество": 2,
"МОЛ": "Дроздова Татьяна Викторовна"
},
{
"Номенклатура": "Материнская плата GIGABYTE LGA1151 H370",
"НоменклатураКод": "00-000000005596",
"Количество": 4,
"МОЛ": "Дроздова Татьяна Викторовна"
},
{
"Номенклатура": "Материнская плата H470 S1200 MATX H470M-HDV ASROCK",
"НоменклатураКод": "00-000000007475",
"Количество": 5,
"МОЛ": "Дроздова Татьяна Викторовна"
},
{
"Номенклатура": "Микросхема, драйвер шагового двигателя Toshiba TB6560AHQ",
"НоменклатураКод": "ОСОООООП9459",
"Количество": 6,
"МОЛ": "Дроздова Татьяна Викторовна"
},
{
"Номенклатура": "Модуль D-Link 330R/10KM/A1A для одномодового оптического кабеля (до 1км)",
"НоменклатураКод": "00-000000004710",
"Количество": 2,
"МОЛ": "Дроздова Татьяна Викторовна"
},
{
"Номенклатура": "Модуль D-Link 330T/10KM/A1A для одномодового оптического кабеля (до 1км)",
"НоменклатураКод": "00-000000004711",
"Количество": 2,
"МОЛ": "Дроздова Татьяна Викторовна"
},
{
"Номенклатура": "Модуль SuperMicro SSD-DM064-SMCMVN1 SATA-DOM 64Gb",
"НоменклатураКод": "00-000000002312",
"Количество": 2,
"МОЛ": "Дроздова Татьяна Викторовна"
},
{
"Номенклатура": "Модуль памяти 8GB Apacer DDR4 2666 DIMM",
"НоменклатураКод": "00-000000003175",
"Количество": 20,
"МОЛ": "Дроздова Татьяна Викторовна"
},
{
"Номенклатура": "Модуль памяти DDR2 - 2gb",
"НоменклатураКод": "П00000001554",
"Количество": 13,
"МОЛ": "Дроздова Татьяна Викторовна"
},
{
"Номенклатура": "Модуль памяти Samsung M378A 5244CBO-CRC DDR4-4Gb 2400,Dimm,OEM",
"НоменклатураКод": "ОСОООООП4572",
"Количество": 1,
"МОЛ": "Дроздова Татьяна Викторовна"
},
{
"Номенклатура": "Модуль памятиApacer DIMM DDR4 8GB 2666",
"НоменклатураКод": "00-000000008821",
"Количество": 20,
"МОЛ": "Дроздова Татьяна Викторовна"
},
{
"Номенклатура": "Монитор 19\" Samsung 940N(KSB) TFT Silver",
"НоменклатураКод": "ОС0000000797",
"Количество": 1,
"МОЛ": "Дроздова Татьяна Викторовна"
},
{
"Номенклатура": "Монитор 19\"ViewSonic VA1948M VGADVI D",
"НоменклатураКод": "00-000000009929",
"Количество": 1,
"МОЛ": "Дроздова Татьяна Викторовна"
},
{
"Номенклатура": "Монитор 21,5\" Philips223VLSB",
"НоменклатураКод": "ОСОООООП4508",
"Количество": 1,
"МОЛ": "Дроздова Татьяна Викторовна"
},
{
"Номенклатура": "Монитор 23,8 ExeGate EP2400A(IPS1920*1080 75Hz 5ms 250cd 1000",
"НоменклатураКод": "00-000000008846",
"Количество": 5,
"МОЛ": "Дроздова Татьяна Викторовна"
},
{
"Номенклатура": "Монитор Viewsonic 21,5''VA2265SMH/VGA/HDMI",
"НоменклатураКод": "00-000000009919",
"Количество": 15,
"МОЛ": "Дроздова Татьяна Викторовна"
},
{
"Номенклатура": "Монитор ViewSonic 24\"VA2448 LED VGADVI D",
"НоменклатураКод": "00-000000009920",
"Количество": 1,
"МОЛ": "Дроздова Татьяна Викторовна"
},
{
"Номенклатура": "Монитор ViewSonic VA1926 w 19\"",
"НоменклатураКод": "00-000000009921",
"Количество": 2,
"МОЛ": "Дроздова Татьяна Викторовна"
},
{
"Номенклатура": "Монитор ViewSonic VA1932 W 19\"",
"НоменклатураКод": "00-000000009923",
"Количество": 1,
"МОЛ": "Дроздова Татьяна Викторовна"
},
{
"Номенклатура": "Монитор ViewSonic VA1932 wa 19\"",
"НоменклатураКод": "00-000000009924",
"Количество": 2,
"МОЛ": "Дроздова Татьяна Викторовна"
},
{
"Номенклатура": "Монитор ViewSonic VA1948M LED",
"НоменклатураКод": "00-000000009928",
"Количество": 1,
"МОЛ": "Дроздова Татьяна Викторовна"
},
{
"Номенклатура": "Монитор ViewSonic VA1948MLED 19\"1440X900",
"НоменклатураКод": "00-000000009925",
"Количество": 1,
"МОЛ": "Дроздова Татьяна Викторовна"
},
{
"Номенклатура": "Монитор ViewSonic VA2232 WA 22\"",
"НоменклатураКод": "00-000000009930",
"Количество": 1,
"МОЛ": "Дроздова Татьяна Викторовна"
},
{
"Номенклатура": "Монитор ViewSonic VA2246m 22\"VGADVI D",
"НоменклатураКод": "00-000000009926",
"Количество": 4,
"МОЛ": "Дроздова Татьяна Викторовна"
},
{
"Номенклатура": "Монитор ViewSonic VA2246m-LED/22",
"НоменклатураКод": "00-000000009912",
"Количество": 1,
"МОЛ": "Дроздова Татьяна Викторовна"
},
{
"Номенклатура": "Монитор ViewSonic VA2246m-Led/22/RGB,DVI-D",
"НоменклатураКод": "00-000000009910",
"Количество": 1,
"МОЛ": "Дроздова Татьяна Викторовна"
},
{
"Номенклатура": "Монитор ViewSonic VA2248-LED FullHD DVI",
"НоменклатураКод": "00-000000009911",
"Количество": 2,
"МОЛ": "Дроздова Татьяна Викторовна"
},
{
"Номенклатура": "Монитор ViewSonic VX1932 wm 19\"",
"НоменклатураКод": "00-000000009927",
"Количество": 1,
"МОЛ": "Дроздова Татьяна Викторовна"
},
{
"Номенклатура": "Монитор_LCD ViewSonic VG1921 19*",
"НоменклатураКод": "00-000000009913",
"Количество": 1,
"МОЛ": "Дроздова Татьяна Викторовна"
},
{
"Номенклатура": "Мышь A4TECH Fstyier FG10, оптическая, беспроводная, USB",
"НоменклатураКод": "00-000000004709",
"Количество": 1,
"МОЛ": "Дроздова Татьяна Викторовна"
},
{
"Номенклатура": "Мышь CBR CM 307 USB",
"НоменклатураКод": "ОСОООООП9523",
"Количество": 7,
"МОЛ": "Дроздова Татьяна Викторовна"
},
{
"Номенклатура": "Мышь Oklick 147M оптическая проводная USB черный",
"НоменклатураКод": "00-000000007531",
"Количество": 1,
"МОЛ": "Дроздова Татьяна Викторовна"
},
{
"Номенклатура": "Мышь USB OPTICAL MM-310 BLACK",
"НоменклатураКод": "00-000000008825",
"Количество": 10,
"МОЛ": "Дроздова Татьяна Викторовна"
},
{
"Номенклатура": "Мышь беспроводная Oklick 485MW.1200dpi.",
"НоменклатураКод": "ОСОООООП7687",
"Количество": 1,
"МОЛ": "Дроздова Татьяна Викторовна"
},
{
"Номенклатура": "Мышь Оклик 147М черный оптическая (1600dpi) USB (4but)",
"НоменклатураКод": "00-000000007474",
"Количество": 5,
"МОЛ": "Дроздова Татьяна Викторовна"
},
{
"Номенклатура": "Мышь проводная",
"НоменклатураКод": "ОСОООООО6422",
"Количество": 2,
"МОЛ": "Дроздова Татьяна Викторовна"
},
{
"Номенклатура": "Набор полых игл для выпаивания (8шт)",
"НоменклатураКод": "00-000000007529",
"Количество": 1,
"МОЛ": "Дроздова Татьяна Викторовна"
},
{
"Номенклатура": "Навигационный приемник UART GPS NEO-7M-C",
"НоменклатураКод": "ОСОООООП9505",
"Количество": 10,
"МОЛ": "Дроздова Татьяна Викторовна"
},
{
"Номенклатура": "Накопитель Patriot SSD 240Gb Burst",
"НоменклатураКод": "ОСОООООП9515",
"Количество": 6,
"МОЛ": "Дроздова Татьяна Викторовна"
},
{
"Номенклатура": "Накопитель QUMO 16Gb USB 2.0 Optiva 02 Pink",
"НоменклатураКод": "00-000000003186",
"Количество": 10,
"МОЛ": "Дроздова Татьяна Викторовна"
},
{
"Номенклатура": "Накопитель SSD 120GB QUMO Novation TLC 3D2.5 (Q3DT-120GMCY) 550/450 MB/s",
"НоменклатураКод": "00-000000007473",
"Количество": 40,
"МОЛ": "Дроздова Татьяна Викторовна"
},
{
"Номенклатура": "Накопитель SSD ExeGate EX280462RUS UV500NextPro+ 2,5\" 256Gb",
"НоменклатураКод": "00-000000003185",
"Количество": 20,
"МОЛ": "Дроздова Татьяна Викторовна"
},
{
"Номенклатура": "Накопитель SSD Netac 128GB 2.5 SATA",
"НоменклатураКод": "00-000000008823",
"Количество": 20,
"МОЛ": "Дроздова Татьяна Викторовна"
},
{
"Номенклатура": "Накопитель SSD Netac 2.5 SATA SA500 240GB",
"НоменклатураКод": "00-000000008824",
"Количество": 54,
"МОЛ": "Дроздова Татьяна Викторовна"
},
{
"Номенклатура": "Накопитель SSD Netac 256GB 2.5 SATA  SA500-256-S3X TLC",
"НоменклатураКод": "00-000000007471",
"Количество": 60,
"МОЛ": "Дроздова Татьяна Викторовна"
},
{
"Номенклатура": "Наушники с микрофоном Logitech Stereo H110 серебристый",
"НоменклатураКод": "00-000000008841",
"Количество": 3,
"МОЛ": "Дроздова Татьяна Викторовна"
},
{
"Номенклатура": "Одноплатный компьютер на базе процессора Broadcom BCM2837",
"НоменклатураКод": "ОСОООООП9497",
"Количество": 2,
"МОЛ": "Дроздова Татьяна Викторовна"
},
{
"Номенклатура": "Оперативная память  QUMO DDR4 DIMM 8GB, 2666MHz",
"НоменклатураКод": "00-000000000426",
"Количество": 5,
"МОЛ": "Дроздова Татьяна Викторовна"
},
{
"Номенклатура": "Оперативная память 1Гб",
"НоменклатураКод": "ОСОООООП2460",
"Количество": 1,
"МОЛ": "Дроздова Татьяна Викторовна"
},
{
"Номенклатура": "Оперативная память 8Гб",
"НоменклатураКод": "ОСОООООП2459",
"Количество": 7,
"МОЛ": "Дроздова Татьяна Викторовна"
},
{
"Номенклатура": "Оперативная память DDR2 2GB DIMM PC2-6400",
"НоменклатураКод": "00-000000005615",
"Количество": 100,
"МОЛ": "Дроздова Татьяна Викторовна"
},
{
"Номенклатура": "Оперативная память DDR3-4gb",
"НоменклатураКод": "П00000001555",
"Количество": 6,
"МОЛ": "Дроздова Татьяна Викторовна"
},
{
"Номенклатура": "Оперативная память DDR4 4GB PC4-19200",
"НоменклатураКод": "ОСОООООП9519",
"Количество": 2,
"МОЛ": "Дроздова Татьяна Викторовна"
},
{
"Номенклатура": "Оперативная память NETAC Basic NTBSD3P16SP-08DDR3-8ГБ 1600МГц",
"НоменклатураКод": "00-000000007472",
"Количество": 30,
"МОЛ": "Дроздова Татьяна Викторовна"
},
{
"Номенклатура": "Оперативная память QUMO DDR3 DIMM 8GB",
"НоменклатураКод": "00-000000005599",
"Количество": 5,
"МОЛ": "Дроздова Татьяна Викторовна"
},
{
"Номенклатура": "Оперативная память QUMO DDR3 DIMM 8GB, 1600MHz",
"НоменклатураКод": "00-000000000425",
"Количество": 6,
"МОЛ": "Дроздова Татьяна Викторовна"
},
{
"Номенклатура": "Оптический патч-корд LC-FC Cabeus F0P(d)-9-LC-FC-20m",
"НоменклатураКод": "00-000000004706",
"Количество": 2,
"МОЛ": "Дроздова Татьяна Викторовна"
},
{
"Номенклатура": "Оптический трансивер Cisco GLC-BX-D=",
"НоменклатураКод": "00-000000000450",
"Количество": 2,
"МОЛ": "Дроздова Татьяна Викторовна"
},
{
"Номенклатура": "Оптический шнур Cabeus simplex",
"НоменклатураКод": "00-000000008872",
"Количество": 8,
"МОЛ": "Дроздова Татьяна Викторовна"
},
{
"Номенклатура": "Оптический шнур Cabeus simplex",
"НоменклатураКод": "00-000000008856",
"Количество": 2,
"МОЛ": "Дроздова Татьяна Викторовна"
},
{
"Номенклатура": "Очиститель печатных плат 400мл.FLUX OFF.REXANT аэрозоль",
"НоменклатураКод": "00-000000007532",
"Количество": 1,
"МОЛ": "Дроздова Татьяна Викторовна"
},
{
"Номенклатура": "Очиститель печатных плат FLUX OFF REXANT 400 мл, аэрозоль",
"НоменклатураКод": "00-000000007514",
"Количество": 4,
"МОЛ": "Дроздова Татьяна Викторовна"
},
{
"Номенклатура": "Очиститель печатных плат FLUX OFF REXANT 400мл",
"НоменклатураКод": "00-000000008840",
"Количество": 4,
"МОЛ": "Дроздова Татьяна Викторовна"
},
{
"Номенклатура": "Память AMD 8GB  DDR4 2666MHzDIMM R7 Performance SeriesBlask R748G2606U2S-UNon-ECC CL16. 1 2V.RTL",
"НоменклатураКод": "00-000000007790",
"Количество": 10,
"МОЛ": "Дроздова Татьяна Викторовна"
},
{
"Номенклатура": "Память Netac 8GB DDR3 1600MHz",
"НоменклатураКод": "00-000000008820",
"Количество": 30,
"МОЛ": "Дроздова Татьяна Викторовна"
},
{
"Номенклатура": "Память SDD Patriot Signature",
"НоменклатураКод": "00-000000003952",
"Количество": 1,
"МОЛ": "Дроздова Татьяна Викторовна"
},
{
"Номенклатура": "Патч-панель PL-12 Cat5-WL- Dual IDC настенная 12 портов",
"НоменклатураКод": "00-000000006910",
"Количество": 6,
"МОЛ": "Дроздова Татьяна Викторовна"
},
{
"Номенклатура": "Патч-панель PL-12-Cat 5-WL-Dual IDC настенная 12 портов",
"НоменклатураКод": "00-000000006906",
"Количество": 8,
"МОЛ": "Дроздова Татьяна Викторовна"
},
{
"Номенклатура": "Переходники Telecom Разветвитель РDMI 1=4 4K@3OHzTTS7005(6937510891733)(.cтрана происхождения Китай",
"НоменклатураКод": "00-000000009157",
"Количество": 4,
"МОЛ": "Дроздова Татьяна Викторовна"
},
{
"Номенклатура": "Пинцеты антистатические (6шт в комплекте)",
"НоменклатураКод": "00-000000007528",
"Количество": 1,
"МОЛ": "Дроздова Татьяна Викторовна"
},
{
"Номенклатура": "Прижимная планка фьюзера в сборе ECOSYS P2235dn/2040dn/M2235",
"НоменклатураКод": "00-000000003201",
"Количество": 10,
"МОЛ": "Дроздова Татьяна Викторовна"
},
{
"Номенклатура": "Прижимная планка фьюзерная в сборе (СЕТ)",
"НоменклатураКод": "00-000000008826",
"Количество": 5,
"МОЛ": "Дроздова Татьяна Викторовна"
},
{
"Номенклатура": "Программируемый контроллер на базе ATmega2560",
"НоменклатураКод": "ОСОООООП9490",
"Количество": 3,
"МОЛ": "Дроздова Татьяна Викторовна"
},
{
"Номенклатура": "Программируемый контроллер на базе ATmega328",
"НоменклатураКод": "ОСОООООП9489",
"Количество": 5,
"МОЛ": "Дроздова Татьяна Викторовна"
},
{
"Номенклатура": "Программно-аппаратный комплекс Rutoken Lite 1010 128КБ серт ФСТЭК",
"НоменклатураКод": "00-000000008851",
"Количество": 4,
"МОЛ": "Дроздова Татьяна Викторовна"
},
{
"Номенклатура": "Процессор CPU Intel Celeron G4900 Coffee Lake OEM",
"НоменклатураКод": "00-000000000428",
"Количество": 2,
"МОЛ": "Дроздова Татьяна Викторовна"
},
{
"Номенклатура": "Процессор CPU Intel Pentium Gold G5400",
"НоменклатураКод": "ОСОООООП9520",
"Количество": 5,
"МОЛ": "Дроздова Татьяна Викторовна"
},
{
"Номенклатура": "Процессор CPU Intel Pentium Gold G5400 Coffee Lake OEM",
"НоменклатураКод": "00-000000005597",
"Количество": 4,
"МОЛ": "Дроздова Татьяна Викторовна"
},
{
"Номенклатура": "Процессор intel Figinnal Pentium Gold G6400",
"НоменклатураКод": "00-000000007497",
"Количество": 5,
"МОЛ": "Дроздова Татьяна Викторовна"
},
{
"Номенклатура": "Процессор intel Original Pentium Gold G6400 Soc-1200(CM8070104291810S RH3Y)",
"НоменклатураКод": "00-000000008849",
"Количество": 5,
"МОЛ": "Дроздова Татьяна Викторовна"
},
{
"Номенклатура": "Радиоуправляемая модель Шорт-корс трака TRAXXAS Slash 2WD RTR 1:10",
"НоменклатураКод": "ОСОООООП2133",
"Количество": 1,
"МОЛ": "Дроздова Татьяна Викторовна"
},
{
"Номенклатура": "Разьем DIN 5pin\"штекер\" пластик на кабель,под пайку ( в комплекте 2шт),страна происхождения : Китай,",
"НоменклатураКод": "00-000000009160",
"Количество": 1,
"МОЛ": "Дроздова Татьяна Викторовна"
},
{
"Номенклатура": "Расходный материал - пластик для 3D -принтера RES HIPS 1.75мм натуральный 750г",
"НоменклатураКод": "00-000000007778",
"Количество": 11,
"МОЛ": "Дроздова Татьяна Викторовна"
},
{
"Номенклатура": "Расходный материал - пластик для 3D- принтера REC АВS 1.75мм серебристый 750г",
"НоменклатураКод": "00-000000007777",
"Количество": 11,
"МОЛ": "Дроздова Татьяна Викторовна"
},
{
"Номенклатура": "Расходный материал - пластик для 3D-принтера REC PLA 1,75мм натуральный 750гр",
"НоменклатураКод": "00-000000007776",
"Количество": 11,
"МОЛ": "Дроздова Татьяна Викторовна"
},
{
"Номенклатура": "Расходный материал- пластик для 3D- принтера REC RELAX 1.75мм белый 750г",
"НоменклатураКод": "00-000000007779",
"Количество": 11,
"МОЛ": "Дроздова Татьяна Викторовна"
},
{
"Номенклатура": "Расширительная плата STM32 Nucleo Pack",
"НоменклатураКод": "ОСОООООП9510",
"Количество": 2,
"МОЛ": "Дроздова Татьяна Викторовна"
},
{
"Номенклатура": "Ролик подачи бумаги Kyocera PATRIS ROLLER",
"НоменклатураКод": "00-000000008831",
"Количество": 5,
"МОЛ": "Дроздова Татьяна Викторовна"
},
{
"Номенклатура": "Роутер Mikro Tik",
"НоменклатураКод": "00-000000007291",
"Количество": 4,
"МОЛ": "Дроздова Татьяна Викторовна"
},
{
"Номенклатура": "Рутокен ЭЦП 3,0 3220",
"НоменклатураКод": "00-000000008845",
"Количество": 1,
"МОЛ": "Дроздова Татьяна Викторовна"
},
{
"Номенклатура": "Сетевая карта",
"НоменклатураКод": "П00000001564",
"Количество": 5,
"МОЛ": "Дроздова Татьяна Викторовна"
},
{
"Номенклатура": "Сетевое оборудование D-Link",
"НоменклатураКод": "00-000000007289",
"Количество": 4,
"МОЛ": "Дроздова Татьяна Викторовна"
},
{
"Номенклатура": "Сетевой адаптер Gigabit Ethemet D- LINK",
"НоменклатураКод": "П00000001580",
"Количество": 5,
"МОЛ": "Дроздова Татьяна Викторовна"
},
{
"Номенклатура": "Системный блок Celeron-D331 2.667MHz/256Mb*2/160,0Gb/DVD+RW",
"НоменклатураКод": "П00000001200",
"Количество": 1,
"МОЛ": "Дроздова Татьяна Викторовна"
},
{
"Номенклатура": "Системный блок Core2Duo/1.86GHz/DDRII1024Mb*2/1 60Gb/DVD+RW",
"НоменклатураКод": "00-000000008573",
"Количество": 5,
"МОЛ": "Дроздова Татьяна Викторовна"
},
{
"Номенклатура": "Смазка premium для установки всех типов термопленок 20г",
"НоменклатураКод": "00-000000007525",
"Количество": 3,
"МОЛ": "Дроздова Татьяна Викторовна"
},
{
"Номенклатура": "Твердотельный накопитель ADATA Ultimate SU650 ASU650SS-120GT-R",
"НоменклатураКод": "00-000000004707",
"Количество": 1,
"МОЛ": "Дроздова Татьяна Викторовна"
},
{
"Номенклатура": "Твердотельный накопитель ADATA Ultimate SU650 ASU650SS-120GT-R",
"НоменклатураКод": "00-000000004703",
"Количество": 6,
"МОЛ": "Дроздова Татьяна Викторовна"
},
{
"Номенклатура": "Твердотельный накопитель SDD 2.5 SATA-3 256Gb",
"НоменклатураКод": "00-000000003953",
"Количество": 1,
"МОЛ": "Дроздова Татьяна Викторовна"
},
{
"Номенклатура": "Термопленка (CET7841) ECOSYS",
"НоменклатураКод": "00-000000008848",
"Количество": 3,
"МОЛ": "Дроздова Татьяна Викторовна"
},
{
"Номенклатура": "Тефлоновый вал Cet CET7849 для Kyocera Ecosys",
"НоменклатураКод": "00-000000008847",
"Количество": 3,
"МОЛ": "Дроздова Татьяна Викторовна"
},
{
"Номенклатура": "Товар CleverMic 101U 5 метров кабель-USB-микрофон,страна происхождения Китай",
"НоменклатураКод": "00-000000009158",
"Количество": 1,
"МОЛ": "Дроздова Татьяна Викторовна"
},
{
"Номенклатура": "Тонер Cactus CS-RK- TL -420X черный флакон 200гр.(в компл.чип) для принтера Pantum P3010/M 6700/V680",
"НоменклатураКод": "00-000000007795",
"Количество": 20,
"МОЛ": "Дроздова Татьяна Викторовна"
},
{
"Номенклатура": "Тонер SC MPT5 1KG черный,кан 1кг",
"НоменклатураКод": "00-000000008834",
"Количество": 8,
"МОЛ": "Дроздова Татьяна Викторовна"
},
{
"Номенклатура": "Тонер Static Control (кан 1кг)",
"НоменклатураКод": "00-000000007513",
"Количество": 25,
"МОЛ": "Дроздова Татьяна Викторовна"
},
{
"Номенклатура": "Тонер Static Control (кан1кг)",
"НоменклатураКод": "00-000000008835",
"Количество": 10,
"МОЛ": "Дроздова Татьяна Викторовна"
},
{
"Номенклатура": "Тонер Static Control TRSUNIV3-1KG черный флакон 1000гр для принтера",
"НоменклатураКод": "00-000000008833",
"Количество": 5,
"МОЛ": "Дроздова Татьяна Викторовна"
},
{
"Номенклатура": "Тонер Картридж Cactus CS-TK 5220BK черный (1200стр) для Kyocera Ecosys M5521 cdn/M5521 cdw/P5021cdn",
"НоменклатураКод": "00-000000007796",
"Количество": 2,
"МОЛ": "Дроздова Татьяна Викторовна"
},
{
"Номенклатура": "Тонер Картридж Cactus CS-TK5220C голубой (1200стр) для Kyocera Ecosys M55221cdn/M5521cdw/P5021cdn/P5",
"НоменклатураКод": "00-000000007797",
"Количество": 1,
"МОЛ": "Дроздова Татьяна Викторовна"
},
{
"Номенклатура": "Тонер Картридж Cactus CS-TK5220M пурпурный (1200стр) для Kyocera Ecosys M5521 cdw/P5021cdn/P5021cdw",
"НоменклатураКод": "00-000000007798",
"Количество": 1,
"МОЛ": "Дроздова Татьяна Викторовна"
},
{
"Номенклатура": "Тонер Картридж Cactys CS-TK5220Y желтый (1200стр) дляKyocera Ecosys M5521cdn/M5521cdw/P5021cdn/P5021",
"НоменклатураКод": "00-000000007799",
"Количество": 1,
"МОЛ": "Дроздова Татьяна Викторовна"
},
{
"Номенклатура": "Транзистор тестер М328 ESR метр",
"НоменклатураКод": "00-000000007477",
"Количество": 1,
"МОЛ": "Дроздова Татьяна Викторовна"
},
{
"Номенклатура": "Трансивер D-Link 30R/10KM/A1A WDM SFP 1*1000Base",
"НоменклатураКод": "00-000000008876",
"Количество": 3,
"МОЛ": "Дроздова Татьяна Викторовна"
},
{
"Номенклатура": "Трансивер D-Link 330T/10KM/A1A 1000Base",
"НоменклатураКод": "00-000000008879",
"Количество": 3,
"МОЛ": "Дроздова Татьяна Викторовна"
},
{
"Номенклатура": "Устройство охлаждения (кулер) Deepcool GAMMA HUNTER",
"НоменклатураКод": "00-000000008822",
"Количество": 10,
"МОЛ": "Дроздова Татьяна Викторовна"
},
{
"Номенклатура": "Фильтр для пылесоса 3М Туре 2, стандартной очистки (Katun/SCS)",
"НоменклатураКод": "00-000000007789",
"Количество": 2,
"МОЛ": "Дроздова Татьяна Викторовна"
},
{
"Номенклатура": "Форм-фактор 3.5\" SATA 500.0gb HITACHI DESKSTAR/Toshiba 32Mb 6Gb",
"НоменклатураКод": "ОСОООООП5636",
"Количество": 3,
"МОЛ": "Дроздова Татьяна Викторовна"
},
{
"Номенклатура": "Фотобарабан OPC Cactus CS-OPC-HP 1505-5 монохромный",
"НоменклатураКод": "00-000000008828",
"Количество": 10,
"МОЛ": "Дроздова Татьяна Викторовна"
},
{
"Номенклатура": "Фотобарабан OPC Cactus CS-OPC-HP-LJ1200",
"НоменклатураКод": "00-000000008829",
"Количество": 10,
"МОЛ": "Дроздова Татьяна Викторовна"
},
{
"Номенклатура": "Фотобарабан OPC Cactus CS-OPS-HP1010-5",
"НоменклатураКод": "00-000000008827",
"Количество": 10,
"МОЛ": "Дроздова Татьяна Викторовна"
},
{
"Номенклатура": "Чернила Epson T664 1 (C13T664 14A)черный (чернила.банка 70 мл для L100/L110/L 132/L200/L210/L222 L3.",
"НоменклатураКод": "00-000000007794",
"Количество": 4,
"МОЛ": "Дроздова Татьяна Викторовна"
},
{
"Номенклатура": "Чернила для EPSON C 13 T66424A Epson L 100 (cyan) 70 мл.",
"НоменклатураКод": "00-000000007791",
"Количество": 1,
"МОЛ": "Дроздова Татьяна Викторовна"
},
{
"Номенклатура": "Чернила оригинальные С 13T664398 (664 M ) для Epson.пурпурный, 6500к,70мл,",
"НоменклатураКод": "00-000000007792",
"Количество": 1,
"МОЛ": "Дроздова Татьяна Викторовна"
},
{
"Номенклатура": "Чернила оригинальные С 13T664498 (664 Y) для Epson. желтый.6500k 70мл",
"НоменклатураКод": "00-000000007793",
"Количество": 1,
"МОЛ": "Дроздова Татьяна Викторовна"
},
{
"Номенклатура": "Шнур оптический duplex LC-LC 9/125 sm 100м LSZH",
"НоменклатураКод": "00-000000005587",
"Количество": 1,
"МОЛ": "Дроздова Татьяна Викторовна"
},
{
"Номенклатура": "Шнур оптический simplex LC-FC 9/125 sm 3м LSZH",
"НоменклатураКод": "00-000000005581",
"Количество": 30,
"МОЛ": "Дроздова Татьяна Викторовна"
}
]
}